{
    "restrictedAreas": [
        {
            "origin": {
                "x": 0.0,
                "y": 0.0
            },
            "position": {
                "x": 0.0,
                "y": 84.0
            },
            "rotation": 0.0,
            "size": {
                "x": 496.0,
                "y": 97.0
            }
        },
        {
            "origin": {
                "x": 0.0,
                "y": 0.0
            },
            "position": {
                "x": 400.0,
                "y": 181.0
            },
            "rotation": 0.0,
            "size": {
                "x": 98.0,
                "y": 458.0
            }
        },
        {
            "origin": {
                "x": 0.0,
                "y": 0.0
            },
            "position": {
                "x": 498.0,
                "y": 543.0
            },
            "rotation": 0.0,
            "size": {
                "x": 212.0,
                "y": 99.0
            }
        },
        {
            "origin": {
                "x": 0.0,
                "y": 0.0
            },
            "position": {
                "x": 614.0,
                "y": 89.0
            },
            "rotation": 0.0,
            "size": {
                "x": 95.0,
                "y": 454.0
            }
        },
        {
            "origin": {
                "x": 0.0,
                "y": 0.0
            },
            "position": {
                "x": 709.0,
                "y": 88.0
            },
            "rotation": 0.0,
            "size": {
                "x": 364.0,
                "y": 97.0
            }
        },
        {
            "origin": {
                "x": 0.0,
                "y": 0.0
            },
            "position": {
                "x": 976.0,
                "y": 184.0
            },
            "rotation": 0.0,
            "size": {
                "x": 98.0,
                "y": 313.0
            }
        },
        {
            "origin": {
                "x": 0.0,
                "y": 0.0
            },
            "position": {
                "x": 1073.0,
                "y": 400.0
            },
            "rotation": 0.0,
            "size": {
                "x": 282.0,
                "y": 98.0
            }
        },
        {
            "origin": {
                "x": 0.0,
                "y": 0.0
            },
            "position": {
                "x": 1259.0,
                "y": 496.0
            },
            "rotation": 0.0,
            "size": {
                "x": 96.0,
                "y": 405.0
            }
        }
    ],
    "waypoints": [
        {
            "x": 36.0,
            "y": 132.0
        },
        {
            "x": 450.0,
            "y": 133.0
        },
        {
            "x": 451.0,
            "y": 600.0
        },
        {
            "x": 662.0,
            "y": 595.0
        },
        {
            "x": 667.0,
            "y": 137.0
        },
        {
            "x": 1027.0,
            "y": 137.0
        },
        {
            "x": 1029.0,
            "y": 454.0
        },
        {
            "x": 1307.0,
            "y": 454.0
        },
        {
            "x": 1309.0,
            "y": 883.0
        }
    ]
}
